LICENSE
README.rst
pyproject.toml
setup.cfg
setup.py
UpSetPlot.egg-info/PKG-INFO
UpSetPlot.egg-info/SOURCES.txt
UpSetPlot.egg-info/dependency_links.txt
UpSetPlot.egg-info/requires.txt
UpSetPlot.egg-info/top_level.txt
upsetplot/__init__.py
upsetplot/data.py
upsetplot/plotting.py
upsetplot/reformat.py
upsetplot/util.py