Metadata-Version: 2.1
Name: UpSetPlot
Version: 0.9.0
Summary: Draw Lex et al.'s UpSet plots with Pandas and Matplotlib
Home-page: https://upsetplot.readthedocs.io
Author: Joel Nothman
Author-email: joel.nothman@gmail.com
License: BSD-3-Clause
Classifier: License :: OSI Approved :: BSD License
Classifier: Programming Language :: Python :: 3
Classifier: Programming Language :: Python :: 3.6
Classifier: Programming Language :: Python :: 3.10
Classifier: Topic :: Scientific/Engineering :: Visualization
Classifier: Intended Audience :: Science/Research
Provides-Extra: testing
License-File: LICENSE
